nba_stats_tracking/__init__.py
nba_stats_tracking/helpers.py
nba_stats_tracking/matchups.py
nba_stats_tracking/models/__init__.py
nba_stats_tracking/models/boxscore/__init__.py
nba_stats_tracking/models/boxscore/boxscore.py
nba_stats_tracking/models/boxscore/request.py
nba_stats_tracking/models/matchups/__init__.py
nba_stats_tracking/models/matchups/matchups.py
nba_stats_tracking/models/matchups/request.py
nba_stats_tracking/models/request.py
nba_stats_tracking/models/scoreboard/__init__.py
nba_stats_tracking/models/scoreboard/request.py
nba_stats_tracking/models/scoreboard/scoreboard.py
nba_stats_tracking/models/tracking/__init__.py
nba_stats_tracking/models/tracking/catch_and_shoot.py
nba_stats_tracking/models/tracking/defense.py
nba_stats_tracking/models/tracking/drives.py
nba_stats_tracking/models/tracking/efficiency.py
nba_stats_tracking/models/tracking/elbow_touches.py
nba_stats_tracking/models/tracking/paint_touches.py
nba_stats_tracking/models/tracking/passing.py
nba_stats_tracking/models/tracking/possessions.py
nba_stats_tracking/models/tracking/post_touches.py
nba_stats_tracking/models/tracking/pull_up.py
nba_stats_tracking/models/tracking/rebounding.py
nba_stats_tracking/models/tracking/request.py
nba_stats_tracking/models/tracking/speed_distance.py
nba_stats_tracking/models/tracking_shots/__init__.py
nba_stats_tracking/models/tracking_shots/request.py
nba_stats_tracking/models/tracking_shots/tracking_shots.py
nba_stats_tracking/tracking.py
nba_stats_tracking/tracking_shots.py
nba_stats_tracking-1.0.8.dist-info/LICENSE
nba_stats_tracking-1.0.8.dist-info/WHEEL
nba_stats_tracking-1.0.8.dist-info/METADATA
nba_stats_tracking-1.0.8.dist-info/RECORD
