Metadata-Version: 2.1
Name: nba-stats-tracking
Version: 1.0.8
Summary: A package to work with NBA player tracking stats using the NBA Stats API
License: MIT
Author: dblackrun
Author-email: darryl.blackport@gmail.com
Requires-Python: >=3.8,<4.0
Classifier: License :: OSI Approved :: MIT License
Classifier: Programming Language :: Python :: 3
Classifier: Programming Language :: Python :: 3.10
Classifier: Programming Language :: Python :: 3.8
Classifier: Programming Language :: Python :: 3.9
Requires-Dist: pydantic (>=1.9.0,<2.0.0)
Requires-Dist: python-dateutil (>=2.8.2,<3.0.0)
Requires-Dist: requests (>=2.27.1,<3.0.0)
